kicad_bom/__about__.py
kicad_bom/__init__.py
kicad_bom/kicad_bom.py
kicad_bom-5.0.1.dist-info/LICENSE
kicad_bom-5.0.1.dist-info/METADATA
kicad_bom-5.0.1.dist-info/WHEEL
kicad_bom-5.0.1.dist-info/top_level.txt
kicad_bom-5.0.1.dist-info/RECORD
