Metadata-Version: 2.1
Name: kicad-bom
Version: 5.0.1
Summary: KiCad Python code for generating bill of materials in multiple formats.
Home-page: https://github.com/janelia-pypi/kicad_bom
Author: Peter Polidoro
Author-email: peter@polidoro.io
License: BSD-3-Clause
Classifier: Programming Language :: Python :: 3
License-File: LICENSE
Requires-Dist: kicad-netlist-reader
